openworld/sdk/fraudpreventiontest/client/order_purchase_screen_client.py
openworld/sdk/fraudpreventiontest/client/order_purchase_update_client.py
openworld/sdk/fraudpreventiontest/model/address.py
openworld/sdk/fraudpreventiontest/model/air.py
openworld/sdk/fraudpreventiontest/model/air_segment.py
openworld/sdk/fraudpreventiontest/model/amount.py
openworld/sdk/fraudpreventiontest/model/authorize.py
openworld/sdk/fraudpreventiontest/model/authorize_reversal.py
openworld/sdk/fraudpreventiontest/model/cancellation_reason.py
openworld/sdk/fraudpreventiontest/model/capture.py
openworld/sdk/fraudpreventiontest/model/car.py
openworld/sdk/fraudpreventiontest/model/chargeback_detail.py
openworld/sdk/fraudpreventiontest/model/chargeback_feedback.py
openworld/sdk/fraudpreventiontest/model/credit_card.py
openworld/sdk/fraudpreventiontest/model/cruise.py
openworld/sdk/fraudpreventiontest/model/customer_account.py
openworld/sdk/fraudpreventiontest/model/device_details.py
openworld/sdk/fraudpreventiontest/model/email.py
openworld/sdk/fraudpreventiontest/model/error.py
openworld/sdk/fraudpreventiontest/model/error_cause.py
openworld/sdk/fraudpreventiontest/model/error_detail.py
openworld/sdk/fraudpreventiontest/model/extended_error.py
openworld/sdk/fraudpreventiontest/model/fraud_decision.py
openworld/sdk/fraudpreventiontest/model/hotel.py
openworld/sdk/fraudpreventiontest/model/insult_detail.py
openworld/sdk/fraudpreventiontest/model/insult_feedback.py
openworld/sdk/fraudpreventiontest/model/insurance.py
openworld/sdk/fraudpreventiontest/model/name.py
openworld/sdk/fraudpreventiontest/model/operations.py
openworld/sdk/fraudpreventiontest/model/order_purchase_screen_request.py
openworld/sdk/fraudpreventiontest/model/order_purchase_screen_response.py
openworld/sdk/fraudpreventiontest/model/order_purchase_transaction.py
openworld/sdk/fraudpreventiontest/model/order_purchase_update_request.py
openworld/sdk/fraudpreventiontest/model/order_update.py
openworld_sdk_python_fraudpreventiontest-6.dist-info/METADATA
openworld_sdk_python_fraudpreventiontest-6.dist-info/WHEEL
openworld_sdk_python_fraudpreventiontest-6.dist-info/top_level.txt
openworld_sdk_python_fraudpreventiontest-6.dist-info/RECORD
