Metadata-Version: 2.1
Name: openworld-sdk-python-fraudpreventiontest
Version: 6
Summary: Open World fraud-prevention-test SDK for Python
Home-page: https://github.com/ExpediaGroup/openworld-sdk-python
Author: Expedia Group
Author-email: oss@expediagroup.com
License: Apache License, Version 2.0
Classifier: Development Status :: 3 - Alpha
Classifier: Programming Language :: Python
Classifier: Programming Language :: Python :: 3 :: Only
Classifier: Programming Language :: Python :: 3
Classifier: Programming Language :: Python :: 3.8
Classifier: Programming Language :: Python :: 3.9
Classifier: Programming Language :: Python :: 3.10
Classifier: Programming Language :: Python :: 3.11
Classifier: License :: OSI Approved :: MIT License
Requires-Python: >=3.8
Requires-Dist: dataclasses-json
Requires-Dist: uri
Requires-Dist: requests
Requires-Dist: furl
Requires-Dist: openworld-sdk-python-core
